[
  { "id": 1, "x": 26.25, "y": 56.25, "angle": 90 },
  { "id": 2, "x": 26.25, "y": 48.75, "angle": 135 },
  { "id": 3, "x": 26.25, "y": 41.25, "angle": 180 },
  { "id": 4, "x": 26.25, "y": 33.75, "angle": 225 },
  { "id": 5, "x": 18.75, "y": 56.25, "angle": 270 },
  { "id": 6, "x": 18.75, "y": 48.75, "angle": 315 },
  { "id": 7, "x": 18.75, "y": 41.25, "angle": 0 },
  { "id": 8, "x": 18.75, "y": 33.75, "angle": 45 },
  { "id": 9, "x": 11.25, "y": 56.25, "angle": 90 },
  { "id": 10, "x": 11.25, "y": 48.75, "angle": 135 },
  { "id": 11, "x": 11.25, "y": 41.25, "angle": 180 },
  { "id": 12, "x": 11.25, "y": 33.75, "angle": 225 },
  { "id": 13, "x": 3.75, "y": 56.25, "angle": 270 },
  { "id": 14, "x": 3.75, "y": 48.75, "angle": 315 },
  { "id": 15, "x": 3.75, "y": 41.25, "angle": 0 },
  { "id": 16, "x": 3.75, "y": 33.75, "angle": 45 },
  { "id": 17, "x": -3.75, "y": 56.25, "angle": 90 },
  { "id": 18, "x": -3.75, "y": 48.75, "angle": 135 },
  { "id": 19, "x": -3.75, "y": 41.25, "angle": 180 },
  { "id": 20, "x": -3.75, "y": 33.75, "angle": 225 },
  { "id": 21, "x": -11.25, "y": 56.25, "angle": 270 },
  { "id": 22, "x": -11.25, "y": 48.75, "angle": 315 },
  { "id": 23, "x": -11.25, "y": 41.25, "angle": 0 },
  { "id": 24, "x": -11.25, "y": 33.75, "angle": 45 },
  { "id": 25, "x": -18.75, "y": 56.25, "angle": 90 },
  { "id": 26, "x": -18.75, "y": 48.75, "angle": 135 },
  { "id": 27, "x": -18.75, "y": 41.25, "angle": 180 },
  { "id": 28, "x": -18.75, "y": 33.75, "angle": 225 },
  { "id": 29, "x": -26.25, "y": 56.25, "angle": 270 },
  { "id": 30, "x": -26.25, "y": 48.75, "angle": 315 },
  { "id": 31, "x": -26.25, "y": 41.25, "angle": 0 },
  { "id": 32, "x": -26.25, "y": 33.75, "angle": 45 },
  { "id": 33, "x": 26.25, "y": 26.25, "angle": 90 },
  { "id": 34, "x": 26.25, "y": 18.75, "angle": 135 },
  { "id": 35, "x": 26.25, "y": 11.25, "angle": 180 },
  { "id": 36, "x": 26.25, "y": 3.75, "angle": 225 },
  { "id": 37, "x": 18.75, "y": 26.25, "angle": 270 },
  { "id": 38, "x": 18.75, "y": 18.75, "angle": 315 },
  { "id": 39, "x": 18.75, "y": 11.25, "angle": 0 },
  { "id": 40, "x": 18.75, "y": 3.75, "angle": 45 },
  { "id": 41, "x": 11.25, "y": 26.25, "angle": 90 },
  { "id": 42, "x": 11.25, "y": 18.75, "angle": 135 },
  { "id": 43, "x": 11.25, "y": 11.25, "angle": 180 },
  { "id": 44, "x": 11.25, "y": 3.75, "angle": 225 },
  { "id": 45, "x": 3.75, "y": 26.25, "angle": 270 },
  { "id": 46, "x": 3.75, "y": 18.75, "angle": 315 },
  { "id": 47, "x": 3.75, "y": 11.25, "angle": 0 },
  { "id": 48, "x": 3.75, "y": 3.75, "angle": 45 },
  { "id": 49, "x": -3.75, "y": 26.25, "angle": 90 },
  { "id": 50, "x": -3.75, "y": 18.75, "angle": 135 },
  { "id": 51, "x": -3.75, "y": 11.25, "angle": 180 },
  { "id": 52, "x": -3.75, "y": 3.75, "angle": 225 },
  { "id": 53, "x": -11.25, "y": 26.25, "angle": 270 },
  { "id": 54, "x": -11.25, "y": 18.75, "angle": 315 },
  { "id": 55, "x": -11.25, "y": 11.25, "angle": 0 },
  { "id": 56, "x": -11.25, "y": 3.75, "angle": 45 },
  { "id": 57, "x": -18.75, "y": 26.25, "angle": 90 },
  { "id": 58, "x": -18.75, "y": 18.75, "angle": 135 },
  { "id": 59, "x": -18.75, "y": 11.25, "angle": 180 },
  { "id": 60, "x": -18.75, "y": 3.75, "angle": 225 },
  { "id": 61, "x": -26.25, "y": 26.25, "angle": 270 },
  { "id": 62, "x": -26.25, "y": 18.75, "angle": 315 },
  { "id": 63, "x": -26.25, "y": 11.25, "angle": 0 },
  { "id": 64, "x": -26.25, "y": 3.75, "angle": 45 },
  { "id": 65, "x": 26.25, "y": -3.75, "angle": 90 },
  { "id": 66, "x": 26.25, "y": -11.25, "angle": 135 },
  { "id": 67, "x": 26.25, "y": -18.75, "angle": 180 },
  { "id": 68, "x": 26.25, "y": -26.25, "angle": 225 },
  { "id": 69, "x": 18.75, "y": -3.75, "angle": 270 },
  { "id": 70, "x": 18.75, "y": -11.25, "angle": 315 },
  { "id": 71, "x": 18.75, "y": -18.75, "angle": 0 },
  { "id": 72, "x": 18.75, "y": -26.25, "angle": 45 },
  { "id": 73, "x": 11.25, "y": -3.75, "angle": 90 },
  { "id": 74, "x": 11.25, "y": -11.25, "angle": 135 },
  { "id": 75, "x": 11.25, "y": -18.75, "angle": 180 },
  { "id": 76, "x": 11.25, "y": -26.25, "angle": 225 },
  { "id": 77, "x": 3.75, "y": -3.75, "angle": 270 },
  { "id": 78, "x": 3.75, "y": -11.25, "angle": 315 },
  { "id": 79, "x": 3.75, "y": -18.75, "angle": 0 },
  { "id": 80, "x": 3.75, "y": -26.25, "angle": 45 },
  { "id": 81, "x": -3.75, "y": -3.75, "angle": 90 },
  { "id": 82, "x": -3.75, "y": -11.25, "angle": 135 },
  { "id": 83, "x": -3.75, "y": -18.75, "angle": 180 },
  { "id": 84, "x": -3.75, "y": -26.25, "angle": 225 },
  { "id": 85, "x": -11.25, "y": -3.75, "angle": 270 },
  { "id": 86, "x": -11.25, "y": -11.25, "angle": 315 },
  { "id": 87, "x": -11.25, "y": -18.75, "angle": 0 },
  { "id": 88, "x": -11.25, "y": -26.25, "angle": 45 },
  { "id": 89, "x": -18.75, "y": -3.75, "angle": 90 },
  { "id": 90, "x": -18.75, "y": -11.25, "angle": 135 },
  { "id": 91, "x": -18.75, "y": -18.75, "angle": 180 },
  { "id": 92, "x": -18.75, "y": -26.25, "angle": 225 },
  { "id": 93, "x": -26.25, "y": -3.75, "angle": 270 },
  { "id": 94, "x": -26.25, "y": -11.25, "angle": 315 },
  { "id": 95, "x": -26.25, "y": -18.75, "angle": 0 },
  { "id": 96, "x": -26.25, "y": -26.25, "angle": 45 },
  { "id": 97, "x": 26.25, "y": -33.75, "angle": 90 },
  { "id": 98, "x": 26.25, "y": -41.25, "angle": 135 },
  { "id": 99, "x": 26.25, "y": -48.75, "angle": 180 },
  { "id": 100, "x": 26.25, "y": -56.25, "angle": 225 },
  { "id": 101, "x": 18.75, "y": -33.75, "angle": 270 },
  { "id": 102, "x": 18.75, "y": -41.25, "angle": 315 },
  { "id": 103, "x": 18.75, "y": -48.75, "angle": 0 },
  { "id": 104, "x": 18.75, "y": -56.25, "angle": 45 },
  { "id": 105, "x": 11.25, "y": -33.75, "angle": 90 },
  { "id": 106, "x": 11.25, "y": -41.25, "angle": 135 },
  { "id": 107, "x": 11.25, "y": -48.75, "angle": 180 },
  { "id": 108, "x": 11.25, "y": -56.25, "angle": 225 },
  { "id": 109, "x": 3.75, "y": -33.75, "angle": 270 },
  { "id": 110, "x": 3.75, "y": -41.25, "angle": 315 },
  { "id": 111, "x": 3.75, "y": -48.75, "angle": 0 },
  { "id": 112, "x": 3.75, "y": -56.25, "angle": 45 },
  { "id": 113, "x": -3.75, "y": -33.75, "angle": 90 },
  { "id": 114, "x": -3.75, "y": -41.25, "angle": 135 },
  { "id": 115, "x": -3.75, "y": -48.75, "angle": 180 },
  { "id": 116, "x": -3.75, "y": -56.25, "angle": 225 },
  { "id": 117, "x": -11.25, "y": -33.75, "angle": 270 },
  { "id": 118, "x": -11.25, "y": -41.25, "angle": 315 },
  { "id": 119, "x": -11.25, "y": -48.75, "angle": 0 },
  { "id": 120, "x": -11.25, "y": -56.25, "angle": 45 },
  { "id": 121, "x": -18.75, "y": -33.75, "angle": 90 },
  { "id": 122, "x": -18.75, "y": -41.25, "angle": 135 },
  { "id": 123, "x": -18.75, "y": -48.75, "angle": 180 },
  { "id": 124, "x": -18.75, "y": -56.25, "angle": 225 },
  { "id": 125, "x": -26.25, "y": -33.75, "angle": 270 },
  { "id": 126, "x": -26.25, "y": -41.25, "angle": 315 },
  { "id": 127, "x": -26.25, "y": -48.75, "angle": 0 },
  { "id": 128, "x": -26.25, "y": -56.25, "angle": 45 }
]
